asciipixels/__init__.py
asciipixels/__main__.py
asciipixels/core.py
asciipixels/typealiases.py
asciipixels/utils.py
asciipixels/image/__init__.py
asciipixels/image/image.py
asciipixels/resources/example.gif
asciipixels/video/__init__.py
asciipixels/video/video.py
asciipixels-0.1.3.dist-info/LICENSE
asciipixels-0.1.3.dist-info/METADATA
asciipixels-0.1.3.dist-info/WHEEL
asciipixels-0.1.3.dist-info/entry_points.txt
asciipixels-0.1.3.dist-info/top_level.txt
asciipixels-0.1.3.dist-info/RECORD
