Metadata-Version: 2.1
Name: asciipixels
Version: 0.1.3
Summary: Generate dynamic ASCII art with images and videos.
Author-email: Leonardo Corona Garza <leocoronag@gmail.com>
License: Copyright (c) 2022 Leonardo Corona Garza        
Keywords: ascii,art,image,video,dynamic
Classifier: License :: OSI Approved :: MIT License
Classifier: Programming Language :: Python
Classifier: Programming Language :: Python :: 3
Requires-Python: >=3.6
License-File: LICENSE
Requires-Dist: Pillow (>=9.0.0)
